qwen3_autogen_client/__init__.py
qwen3_autogen_client/qwen_client.py
qwen3_autogen_client-0.1.4.dist-info/licenses/LICENSE
qwen3_autogen_client-0.1.4.dist-info/METADATA
qwen3_autogen_client-0.1.4.dist-info/WHEEL
qwen3_autogen_client-0.1.4.dist-info/top_level.txt
qwen3_autogen_client-0.1.4.dist-info/RECORD
