Metadata-Version: 2.4
Name: qwen3-autogen-client
Version: 0.1.4
Summary: A Python client for Qwen and DeepSeek models with AutoGen, supporting structured outputs and function calling.
Author-email: Shamit Verma <oss@shamit.in>
License: Apache-2.0
Project-URL: Homepage, https://github.com/shamitv/autogen-local-llm-client-qwen
Project-URL: Bug Tracker, https://github.com/shamitv/autogen-local-llm-client-qwen/issues
Classifier: Programming Language :: Python :: 3
Classifier: License :: OSI Approved :: MIT License
Classifier: Operating System :: OS Independent
Classifier: Intended Audience :: Developers
Classifier: Topic :: Scientific/Engineering :: Artificial Intelligence
Requires-Python: >=3.8
License-File: LICENSE
Requires-Dist: autogen-ext[openai]
Requires-Dist: python-dotenv
Requires-Dist: pydantic
Requires-Dist: autogen-core
Dynamic: license-file
